gabber/__init__.py
gabber/client.py
gabber-0.1.2.dist-info/LICENSE.md
gabber-0.1.2.dist-info/METADATA
gabber-0.1.2.dist-info/WHEEL
gabber-0.1.2.dist-info/entry_points.txt
gabber-0.1.2.dist-info/RECORD
