Metadata-Version: 2.1
Name: gabber
Version: 0.1.2
Summary: Gabber is a tool for scraping and analyzing Gab posts.
Author: R. Miles McCain
Author-email: mccain@stanford.edu
Requires-Python: >=3.8,<4.0
Classifier: Programming Language :: Python :: 3
Classifier: Programming Language :: Python :: 3.8
Classifier: Programming Language :: Python :: 3.9
Classifier: Programming Language :: Python :: 3.10
Classifier: Programming Language :: Python :: 3.11
Requires-Dist: beautifulsoup4 (>=4.10.0,<5.0.0)
Requires-Dist: click (>=8.0.1,<9.0.0)
Requires-Dist: curl-cffi (>=0.5.3,<0.6.0)
Requires-Dist: loguru (>=0.6.0,<0.7.0)
Requires-Dist: python-dateutil (>=2.8.2,<3.0.0)
Requires-Dist: ratelimit (>=2.2.1,<3.0.0)
Requires-Dist: requests (>=2.31.0,<3.0.0)
Requires-Dist: selenium (>=4.3.0,<5.0.0)
Requires-Dist: tqdm (>=4.62.1,<5.0.0)
Requires-Dist: undetected-chromedriver (>=3.1.5,<4.0.0)
